CHANGES.txt
MANIFEST.in
README.rst
requirements.txt
setup.py
MegaScreen/__init__.py
MegaScreen.egg-info/PKG-INFO
MegaScreen.egg-info/SOURCES.txt
MegaScreen.egg-info/dependency_links.txt
MegaScreen.egg-info/requires.txt
MegaScreen.egg-info/top_level.txt
tests/README.rst
tests/Zernike.py
tests/interferometer_spectrum.py
tests/noll_mystery.py
tests/structure_function.py
tests/theory.py
tests/zernike_decomposition.py
tests/.ipynb_checkpoints/Noll tests-checkpoint.py
tests/.ipynb_checkpoints/interferometer_spectrum-checkpoint.py
tests/.ipynb_checkpoints/noll_mystery-Copy1-checkpoint.py
tests/.ipynb_checkpoints/noll_mystery-checkpoint.py
tests/.ipynb_checkpoints/structure_function-checkpoint.py
tests/.ipynb_checkpoints/zernike_decomposition-Copy1-checkpoint.py
tests/.ipynb_checkpoints/zernike_decomposition-checkpoint.py
tests/cache/joblib/__main__--Users-dfb-Research-Projects-MegaScreen-tests-__ipython-input__/MemoWinker/func_code.py
tests/demos/context.py
tests/demos/play_movie.py
tests/demos/speckle_movie.py
tests/demos/streamlit_movie.py
tests/demos/.ipynb_checkpoints/speckle_movie-checkpoint.py
tests/plots_for_paper/Plots for paper.py